fast_jwt/__init__.py
fast_jwt_auth-0.1.8.dist-info/licenses/LICENSE
fast_jwt_auth-0.1.8.dist-info/METADATA
fast_jwt_auth-0.1.8.dist-info/WHEEL
fast_jwt_auth-0.1.8.dist-info/top_level.txt
fast_jwt_auth-0.1.8.dist-info/RECORD
